Night/__init__.py
Night/main.py
mr_hawk-0.1.dist-info/METADATA
mr_hawk-0.1.dist-info/WHEEL
mr_hawk-0.1.dist-info/entry_points.txt
mr_hawk-0.1.dist-info/top_level.txt
mr_hawk-0.1.dist-info/RECORD
